Metadata-Version: 1.0
Name: agi-probability
Version: 0.1
Summary: Package agi_probability
Home-page: UNKNOWN
Author: UNKNOWN
Author-email: UNKNOWN
License: UNKNOWN
Platform: UNKNOWN
